{"_type":"export","__export_format":4,"__export_date":"2021-08-05T21:43:05.165Z","__export_source":"insomnia.desktop.app:v2021.4.1","resources":[{"_id":"req_440fc318b18b4a7db706687f3ad93c9c","parentId":"wrk_12ff6d0c18004a4689159254201b1d5f","modified":1628199745738,"created":1625432128763,"url":"localhost:2145/users","name":"login","description":"","method":"POST","body":{"mimeType":"application/json","text":"{\n\t\"name\": \"carlos\",\n\t\"password\":\"1456\",\n\t\"email\": \"junior@hbb\",\n\t\"interests\": [{\"id\": 3},{\"id\": 4}]\n}"},"parameters":[],"headers":[{"name":"Content-Type","value":"application/json","id":"pair_8d7a05ad57144bccabcb85ac6ddc9a2b"}],"authentication":{},"metaSortKey":-1625432128763,"isPrivate":false,"settingStoreCookies":true,"settingSendCookies":true,"settingDisableRenderRequestBody":false,"settingEncodeUrl":true,"settingRebuildPath":true,"settingFollowRedirects":"global","_type":"request"},{"_id":"wrk_12ff6d0c18004a4689159254201b1d5f","parentId":null,"modified":1625430523216,"created":1625430523216,"name":"Insomnia","description":"","scope":"collection","_type":"workspace"},{"_id":"req_4f254805c80449c2b4086587b45422af","parentId":"wrk_12ff6d0c18004a4689159254201b1d5f","modified":1628197090171,"created":1628172635220,"url":"localhost:2145/users/32","name":"getOne","description":"","method":"GET","body":{"mimeType":"multipart/form-data","params":[]},"parameters":[],"headers":[{"name":"Content-Type","value":"multipart/form-data","id":"pair_8d7a05ad57144bccabcb85ac6ddc9a2b"}],"authentication":{},"metaSortKey":-1625432128713,"isPrivate":false,"settingStoreCookies":true,"settingSendCookies":true,"settingDisableRenderRequestBody":false,"settingEncodeUrl":true,"settingRebuildPath":true,"settingFollowRedirects":"global","_type":"request"},{"_id":"req_6731bd05a4b246ae99c9088f4a8db602","parentId":"wrk_12ff6d0c18004a4689159254201b1d5f","modified":1628191243653,"created":1628190941898,"url":"localhost:2145/users","name":"findAll","description":"","method":"GET","body":{"mimeType":"multipart/form-data","params":[]},"parameters":[],"headers":[{"name":"Content-Type","value":"multipart/form-data","id":"pair_8d7a05ad57144bccabcb85ac6ddc9a2b"}],"authentication":{},"metaSortKey":-1625432128663,"isPrivate":false,"settingStoreCookies":true,"settingSendCookies":true,"settingDisableRenderRequestBody":false,"settingEncodeUrl":true,"settingRebuildPath":true,"settingFollowRedirects":"global","_type":"request"},{"_id":"req_39ea95178de640a687107a9a8acba810","parentId":"wrk_12ff6d0c18004a4689159254201b1d5f","modified":1628199762801,"created":1628196758282,"url":"localhost:2145/users/32","name":"update","description":"","method":"PATCH","body":{"mimeType":"application/json","text":"{\n\t\"interests\": [{\"id\": 2},{\"id\": 3}]\n}"},"parameters":[],"headers":[{"name":"Content-Type","value":"application/json","id":"pair_8d7a05ad57144bccabcb85ac6ddc9a2b"}],"authentication":{},"metaSortKey":-1625432128613,"isPrivate":false,"settingStoreCookies":true,"settingSendCookies":true,"settingDisableRenderRequestBody":false,"settingEncodeUrl":true,"settingRebuildPath":true,"settingFollowRedirects":"global","_type":"request"},{"_id":"env_6cf6b6429bc4eb1ebcb9caad9167b9a6fba2e866","parentId":"wrk_12ff6d0c18004a4689159254201b1d5f","modified":1625430523292,"created":1625430523292,"name":"Base Environment","data":{},"dataPropertyOrder":null,"color":null,"isPrivate":false,"metaSortKey":1625430523292,"_type":"environment"},{"_id":"jar_6cf6b6429bc4eb1ebcb9caad9167b9a6fba2e866","parentId":"wrk_12ff6d0c18004a4689159254201b1d5f","modified":1625809748630,"created":1625430523295,"name":"Default Jar","cookies":[{"key":"Token","value":"W5wAfawMu6sJj7dEeg7rlhNMYxQdOKF.13370","expires":"2021-08-09T05:47:48.000Z","domain":"myprofitweb.com","path":"/","hostOnly":true,"creation":"2021-07-04T21:09:48.125Z","lastAccessed":"2021-07-09T05:49:08.618Z","id":"550872358321274"}],"_type":"cookie_jar"},{"_id":"spc_92d289e6405e4fa3a82bef9c647e6d3b","parentId":"wrk_12ff6d0c18004a4689159254201b1d5f","modified":1625430523218,"created":1625430523218,"fileName":"Insomnia","contents":"","contentType":"yaml","_type":"api_spec"}]}